lab4/src/matrix_vector_multiplier.v
// POWER-OPT: Operand Isolation + clean enables (clock-gating friendly)
module matrix_vector_multiplier #(
    parameter N     = 3,
    parameter WIDTH = 8
)(
    input  wire                   clk,
    input  wire                   rst_n,   // Active-low async reset
    input  wire                   ena,     // Start pulse/level

    input  wire signed [N*N*WIDTH-1:0] matrix_a,
    input  wire signed [N*WIDTH-1:0]   vector_b,

    output reg  signed [N*WIDTH-1:0]   vector_c,
    output reg                         done
);

    // --- INTERNAL PARAMETERS ---
    localparam CNT_WIDTH   = (N <= 1) ? 1 : $clog2(N);
    localparam ACCUM_WIDTH = (2*WIDTH) + $clog2(N);

    // --- INTERNAL STORAGE ---
    reg signed [WIDTH-1:0]       mat_a [0:N-1][0:N-1];
    reg signed [WIDTH-1:0]       vec_b [0:N-1];
    reg signed [ACCUM_WIDTH-1:0] vec_c_internal [0:N-1];

    // --- FSM ---
    reg [1:0] state;
    localparam STATE_IDLE    = 2'b00;
    localparam STATE_LOAD    = 2'b01;
    localparam STATE_COMPUTE = 2'b10;
    localparam STATE_DONE    = 2'b11;

    // --- Counters ---
    reg [CNT_WIDTH-1:0] i, k;
    reg [CNT_WIDTH-1:0] row, col;

    // --- Enables (for fine-grained gating) ---
    wire load_en    = (state == STATE_LOAD);
    wire compute_en = (state == STATE_COMPUTE);
    wire done_en    = (state == STATE_DONE);

    // --- Operand Isolation ---
    // Keep multiplier inputs at 0 unless actually computing this MAC.
    // This is synthesized as AND-gates / muxes on the operand buses.
    wire signed [WIDTH-1:0] iso_a = compute_en ? mat_a[i][k] : '0;
    wire signed [WIDTH-1:0] iso_b = compute_en ? vec_b[k]    : '0;

    // Optional: short-circuit the adder when a zero operand is detected.
    // This avoids toggling in the accumulator adder when the product is 0.
    wire prod_is_zero = (iso_a == '0) || (iso_b == '0);
    wire signed [2*WIDTH-1:0] product = iso_a * iso_b;

    integer r, c; // for generate-style loops below

    // --- SEQUENTIAL ---
    always @(posedge clk or negedge rst_n) begin
        if (!rst_n) begin
            state <= STATE_IDLE;
            done  <= 1'b0;
            i     <= '0;
            k     <= '0;

            // Reset accumulators (using named loop vars to avoid synthesis warnings)
            for (r = 0; r < N; r = r + 1) begin
                vec_c_internal[r] <= '0;
            end

            // (Leaving mat_a/vec_b uninitialized on reset is fine; they are loaded in STATE_LOAD)
        end else begin
            // Default “hold” to avoid unnecessary toggles
            done <= 1'b0;

            case (state)
                // ---------------- IDLE ----------------
                STATE_IDLE: begin
                    if (ena) begin
                        i <= '0;
                        k <= '0;
                        for (r = 0; r < N; r = r + 1) begin
                            vec_c_internal[r] <= '0;
                        end
                        state <= STATE_LOAD;
                    end
                end

                // ---------------- LOAD ----------------
                STATE_LOAD: begin
                    // Only write when loading (write-enable serves as clock-gating hint)
                    if (load_en) begin
                        for (row = 0; row < N; row = row + 1) begin
                            for (col = 0; col < N; col = col + 1) begin
                                mat_a[row][col] <= matrix_a[(row*N+col)*WIDTH +: WIDTH];
                            end
                            vec_b[row] <= vector_b[row*WIDTH +: WIDTH];
                            vec_c_internal[row] <= '0;
                        end
                        i <= '0;
                        k <= '0;
                    end
                    state <= STATE_COMPUTE;
                end

                // ---------------- COMPUTE ----------------
                STATE_COMPUTE: begin
                    // MAC with operand isolation:
                    // If product is zero, skip accumulator write to avoid toggling.
                    if (!prod_is_zero) begin
                        vec_c_internal[i] <= vec_c_internal[i] + {{(ACCUM_WIDTH-(2*WIDTH)){product[2*WIDTH-1]}}, product};
                    end
                    // If product is zero, we hold vec_c_internal[i] (no write).

                    // Counter progression
                    if (k == N-1) begin
                        k <= '0;
                        if (i == N-1) begin
                            i <= '0;
                            state <= STATE_DONE;
                        end else begin
                            i <= i + 1'b1;
                        end
                    end else begin
                        k <= k + 1'b1;
                    end
                end

                // ---------------- DONE ----------------
                STATE_DONE: begin
                    if (done_en) begin
                        for (row = 0; row < N; row = row + 1) begin
                            // Truncate/saturate policy: here we truncate to WIDTH
                            vector_c[row*WIDTH +: WIDTH] <= vec_c_internal[row][WIDTH-1:0];
                        end
                        done  <= 1'b1;
                    end
                    state <= STATE_IDLE;
                end

                default: state <= STATE_IDLE;
            endcase
        end
    end

endmodule

lab4/src/matrix_vector_multiplier_baseline.v
// Synthesizable NxN Matrix by Nx1 Vector Multiplication Accelerator
// (Fully parameterized, Verilog-2005 compatible)

module matrix_vector_multiplier_baseline #(
    parameter N     = 3, // Matrix/Vector dimension (e.g., 3 for 3x3)
    parameter WIDTH = 8  // Bit-width for each element
)(
    input  wire                   clk,
    input  wire                   rst_n,   // Active-low asynchronous reset
    input  wire                   ena,     // Enable signal to start multiplication

    // PARAMETERIZED Input Ports
    // Flat bus for the NxN matrix: (N*N*WIDTH) total bits
    input  wire signed [N*N*WIDTH-1:0] matrix_a,
    // Flat bus for the Nx1 vector: (N*WIDTH) total bits
    input  wire signed [N*WIDTH-1:0]   vector_b,

    // PARAMETERIZED Output Ports
    // Flat bus for the Nx1 result: (N*WIDTH) total bits
    output reg  signed [N*WIDTH-1:0]   vector_c,
    output reg                         done     // High when the result is ready
);

    // --- INTERNAL PARAMETERS ---
    
    // Calculate the width for our loop counters (e.g., for N=3, we need 2 bits)
    localparam CNT_WIDTH = $clog2(N);

    // Calculate the width for the internal accumulator
    // Product width = WIDTH * WIDTH => 2*WIDTH
    // We add N of these products. Sum can grow by $clog2(N) bits.
    localparam ACCUM_WIDTH = (2 * WIDTH) + $clog2(N);

    // --- INTERNAL STORAGE ---
    
    // PARAMETERIZED 2D register for the matrix and 1D for the vectors
    reg signed [WIDTH-1:0]       mat_a [0:N-1][0:N-1];
    reg signed [WIDTH-1:0]       vec_b [0:N-1];
    reg signed [ACCUM_WIDTH-1:0] vec_c_internal [0:N-1]; // Wider for accumulation

    // --- FSM AND COUNTERS ---
    reg [1:0] state;
    localparam STATE_IDLE    = 2'b00;
    localparam STATE_LOAD    = 2'b01;
    localparam STATE_COMPUTE = 2'b10;
    localparam STATE_DONE    = 2'b11;

    // PARAMETERIZED loop counters
    reg [CNT_WIDTH-1:0] i, k;    // Loop indices for rows and inner product
    reg [CNT_WIDTH-1:0] row, col; // Loop iterators for loading/storing

    // On every clock cycle, manage the state machine
    always @(posedge clk or negedge rst_n) begin
        if (!rst_n) begin
            // --- RESET STATE ---
            state <= STATE_IDLE;
            done  <= 1'b0;
            i     <= 0;
            k     <= 0;
        end else begin
            case (state)
                STATE_IDLE: begin
                    done <= 1'b0;
                    if (ena) begin
                        state <= STATE_LOAD; // Start on enable signal
                    end
                end

                STATE_LOAD: begin
                    // --- LOAD AND UNPACK INPUTS ---
                    // This 'for' loop is unrolled by the synthesizer
                    for (row = 0; row < N; row = row + 1) begin
                        for (col = 0; col < N; col = col + 1) begin
                            // PARAMETERIZED unpacking logic
                            mat_a[row][col] <= matrix_a[(row*N+col)*WIDTH +: WIDTH];
                        end
                        vec_b[row] <= vector_b[row*WIDTH +: WIDTH];
                        vec_c_internal[row] <= 0; // Clear previous result
                    end
                    i <= 0;
                    k <= 0;
                    state <= STATE_COMPUTE;
                end

                STATE_COMPUTE: begin
                    // --- PERFORM ONE MULTIPLY-ACCUMULATE PER CYCLE ---
                    // C[i] = C[i] + A[i][k] * B[k]
                    vec_c_internal[i] <= vec_c_internal[i] + (mat_a[i][k] * vec_b[k]);

                    // --- PARAMETERIZED LOOP COUNTER UPDATE ---
                    if (k == N-1) begin
                        k <= 0;
                        if (i == N-1) begin
                            i <= 0;
                            state <= STATE_DONE; // Finished all computations
                        end else begin
                            i <= i + 1;
                        end
                    end else begin
                        k <= k + 1;
                    end
                end

                STATE_DONE: begin
                    // --- PACK 1D RESULT VECTOR INTO OUTPUT ---
                    // This 'for' loop is also unrolled
                    for (row = 0; row < N; row = row + 1) begin
                        // PARAMETERIZED packing logic
                        // NOTE: This truncates the wide accumulator result!
                        vector_c[row*WIDTH +: WIDTH] <= vec_c_internal[row][WIDTH-1:0];
                    end
                    done  <= 1'b1;
                    state <= STATE_IDLE; // Return to idle
                end

                default: begin
                    state <= STATE_IDLE;
                end
            endcase
        end
    end

endmodule

lab4/src/matrix_vector_multiplier_opt_tb.v
`timescale 1ns/1ps

// Testbench compares the OPT design (matrix_vector_multiplier)
// against the baseline (matrix_vector_multiplier_baseline)
// using only Verilog-2001 constructs, no SV-only features.

module matrix_vector_multiplier_opt_tb;

  // -------- Parameters --------
  localparam integer N          = 3;
  localparam integer WIDTH      = 8;
  localparam integer CLK_PERIOD = 25;

  // Derived widths
  localparam integer MATRIX_A_WIDTH = N*N*WIDTH;
  localparam integer VECTOR_B_WIDTH = N*WIDTH;
  localparam integer VECTOR_C_WIDTH = N*WIDTH;

  // -------- DUT I/O --------
  reg                      clk;
  reg                      rst_n;
  reg                      ena;

  reg  signed [MATRIX_A_WIDTH-1:0] matrix_a;  // flattened N×N matrix
  reg  signed [VECTOR_B_WIDTH-1:0] vector_b;  // flattened N vector

  wire signed [VECTOR_C_WIDTH-1:0] vector_c_baseline;
  wire                             done_baseline;

  wire signed [VECTOR_C_WIDTH-1:0] vector_c_opt;
  wire                             done_opt;

  // -------- Instantiate Baseline DUT --------
  matrix_vector_multiplier_baseline #(
    .N(N), .WIDTH(WIDTH)
  ) dut_baseline (
    .clk      (clk),
    .rst_n    (rst_n),
    .ena      (ena),
    .matrix_a (matrix_a),
    .vector_b (vector_b),
    .vector_c (vector_c_baseline),
    .done     (done_baseline)
  );

  // -------- Instantiate Optimized DUT --------
  matrix_vector_multiplier #(
    .N(N), .WIDTH(WIDTH)
  ) dut_opt (
    .clk      (clk),
    .rst_n    (rst_n),
    .ena      (ena),
    .matrix_a (matrix_a),
    .vector_b (vector_b),
    .vector_c (vector_c_opt),
    .done     (done_opt)
  );

  // -------- Clock --------
  initial begin
    clk = 1'b0;
    forever #(CLK_PERIOD/2) clk = ~clk;
  end

  // -------- Simple reset task --------
  task do_reset;
  begin
    rst_n    = 1'b0;
    ena      = 1'b0;
    matrix_a = {MATRIX_A_WIDTH{1'b0}};
    vector_b = {VECTOR_B_WIDTH{1'b0}};
    repeat (3) @(posedge clk);
    rst_n = 1'b1;
    @(posedge clk);
  end
  endtask

  // -------- Apply one stimulus and check equality --------
  task apply_and_check(
    input signed [MATRIX_A_WIDTH-1:0] m,
    input signed [VECTOR_B_WIDTH-1:0] v
  );
  begin
    // Drive inputs
    matrix_a <= m;
    vector_b <= v;

    // Pulse enable for one cycle
    @(posedge clk);
    ena <= 1'b1;
    @(posedge clk);
    ena <= 1'b0;

    // Wait for both designs to assert done
    wait(done_baseline && done_opt);
    @(posedge clk);

    // Compare results (bit-accurate)
    if (vector_c_opt !== vector_c_baseline) begin
      $display("[%0t] FAIL", $time);
      $display("  baseline: %0d (0x%0h)", $signed(vector_c_baseline), vector_c_baseline);
      $display("  opt     : %0d (0x%0h)", $signed(vector_c_opt),      vector_c_opt);
      $fatal;
    end else begin
      $display("[%0t] PASS -> c = %0d (0x%0h)",
               $time, $signed(vector_c_opt), vector_c_opt);
    end
  end
  endtask

  // -------- Test sequence --------
  initial begin
    // Waves
    $dumpfile("opt_vs_baseline_waves.vcd");
    $dumpvars(0, matrix_vector_multiplier_opt_tb);

    // Reset
    do_reset();

    // ========== Packing convention ==========
    // We pack MSB-first in concatenations below.
    // For matrix_a: {a00, a01, a02, a10, a11, a12, a20, a21, a22}
    // For vector_b: {b0, b1, b2}
    // Make sure your DUTs use the same convention.

    // -------- TC1: Simple Positive Values --------
    $display("---- TC1: simple positive ----");
    apply_and_check(
      // A = [[1,2,3],[4,5,6],[7,8,9]]
      {
        8'sd1, 8'sd2, 8'sd3,
        8'sd4, 8'sd5, 8'sd6,
        8'sd7, 8'sd8, 8'sd9
      },
      // b = [1,2,3]
      { 8'sd1, 8'sd2, 8'sd3 }
    );

    // -------- TC2: Identity Matrix --------
    $display("---- TC2: identity * vector ----");
    apply_and_check(
      // A = I3
      {
        8'sd1, 8'sd0, 8'sd0,
        8'sd0, 8'sd1, 8'sd0,
        8'sd0, 8'sd0, 8'sd1
      },
      // b = [2,7,99]
      { 8'sd2, 8'sd7, 8'sd99 }
    );

    // -------- TC3: Zero Vector --------
    $display("---- TC3: zero vector ----");
    apply_and_check(
      {
        8'sd33, 8'sd22, 8'sd85,
        8'sd11, 8'sd99, 8'sd45,
        8'sd77, 8'sd66, 8'sd19
      },
      { 8'sd0, 8'sd0, 8'sd0 }
    );

    // -------- TC4: Min/Max Stress (signed) --------
    $display("---- TC4: min/max signed ----");
    // A rows: [-127 -127 -127], [-1 -1 1], [127 127 127]
    apply_and_check(
      {
        -8'sd127, -8'sd127, -8'sd127,
        -8'sd1,   -8'sd1,    8'sd1,
         8'sd127,  8'sd127,  8'sd127
      },
      { 8'sd127, 8'sd127, 8'sd127 }
    );

    // -------- TC5: Mixed signs --------
    $display("---- TC5: mixed signs ----");
    apply_and_check(
      {
         8'sd10,  -8'sd3,  8'sd5,
        -8'sd8,    8'sd12, 8'sd0,
         8'sd7,    8'sd1, -8'sd2
      },
      { -8'sd4, 8'sd9, 8'sd3 }
    );

    $display("[%0t] All tests passed.", $time);
    $finish;
  end

endmodule

lab4/opt_vs_baseline_waves.vcd
$date
	Wed Oct 29 11:17:45 2025
$end
$version
	Icarus Verilog
$end
$timescale
	1ps
$end
$scope module matrix_vector_multiplier_opt_tb $end
$var wire 24 ! vector_c_opt [23:0] $end
$var wire 24 " vector_c_baseline [23:0] $end
$var wire 1 # done_opt $end
$var wire 1 $ done_baseline $end
$var parameter 32 % CLK_PERIOD $end
$var parameter 32 & MATRIX_A_WIDTH $end
$var parameter 32 ' N $end
$var parameter 32 ( VECTOR_B_WIDTH $end
$var parameter 32 ) VECTOR_C_WIDTH $end
$var parameter 32 * WIDTH $end
$var reg 1 + clk $end
$var reg 1 , ena $end
$var reg 72 - matrix_a [71:0] $end
$var reg 1 . rst_n $end
$var reg 24 / vector_b [23:0] $end
$scope module dut_baseline $end
$var wire 1 + clk $end
$var wire 1 , ena $end
$var wire 72 0 matrix_a [71:0] $end
$var wire 1 . rst_n $end
$var wire 24 1 vector_b [23:0] $end
$var parameter 65 2 ACCUM_WIDTH $end
$var parameter 32 3 CNT_WIDTH $end
$var parameter 32 4 N $end
$var parameter 2 5 STATE_COMPUTE $end
$var parameter 2 6 STATE_DONE $end
$var parameter 2 7 STATE_IDLE $end
$var parameter 2 8 STATE_LOAD $end
$var parameter 32 9 WIDTH $end
$var reg 2 : col [1:0] $end
$var reg 1 $ done $end
$var reg 2 ; i [1:0] $end
$var reg 2 < k [1:0] $end
$var reg 2 = row [1:0] $end
$var reg 2 > state [1:0] $end
$var reg 24 ? vector_c [23:0] $end
$upscope $end
$scope module dut_opt $end
$var wire 1 + clk $end
$var wire 1 , ena $end
$var wire 72 @ matrix_a [71:0] $end
$var wire 1 A prod_is_zero $end
$var wire 1 . rst_n $end
$var wire 24 B vector_b [23:0] $end
$var wire 16 C product [15:0] $end
$var wire 1 D load_en $end
$var wire 8 E iso_b [7:0] $end
$var wire 8 F iso_a [7:0] $end
$var wire 1 G done_en $end
$var wire 1 H compute_en $end
$var parameter 65 I ACCUM_WIDTH $end
$var parameter 32 J CNT_WIDTH $end
$var parameter 32 K N $end
$var parameter 2 L STATE_COMPUTE $end
$var parameter 2 M STATE_DONE $end
$var parameter 2 N STATE_IDLE $end
$var parameter 2 O STATE_LOAD $end
$var parameter 32 P WIDTH $end
$var reg 2 Q col [1:0] $end
$var reg 1 # done $end
$var reg 2 R i [1:0] $end
$var reg 2 S k [1:0] $end
$var reg 2 T row [1:0] $end
$var reg 2 U state [1:0] $end
$var reg 24 V vector_c [23:0] $end
$var integer 32 W r [31:0] $end
$upscope $end
$scope task apply_and_check $end
$var reg 72 X m [71:0] $end
$var reg 24 Y v [23:0] $end
$upscope $end
$scope task do_reset $end
$upscope $end
$upscope $end
$enddefinitions $end
$comment Show the parameter values. $end
$dumpall
b1000 P
b1 O
b0 N
b11 M
b10 L
b11 K
b10 J
b10010 I
b1000 9
b1 8
b0 7
b11 6
b10 5
b11 4
b10 3
b10010 2
b1000 *
b11000 )
b11000 (
b11 '
b1001000 &
b11001 %
$end
#0
$dumpvars
bx Y
bx X
b11 W
bx V
b0 U
bx T
b0 S
b0 R
bx Q
0H
0G
b0 F
b0 E
0D
b0 C
b0 B
1A
b0 @
bx ?
b0 >
bx =
b0 <
b0 ;
bx :
b0 1
b0 0
b0 /
0.
b0 -
0,
0+
0$
0#
bx "
bx !
$end
#12000
b11 W
1+
#24000
0+
#36000
b11 W
1+
#48000
0+
#60000
1.
1+
#72000
0+
#84000
b10000001000000011 /
b10000001000000011 1
b10000001000000011 B
b10000001000000011000001000000010100000110000001110000100000001001 -
b10000001000000011000001000000010100000110000001110000100000001001 0
b10000001000000011000001000000010100000110000001110000100000001001 @
b10000001000000011 Y
b10000001000000011000001000000010100000110000001110000100000001001 X
1+
#96000
0+
#108000
1,
1+
#120000
0+
#132000
b1 >
1D
b1 U
0,
b11 W
1+
#144000
0+
#156000
0A
b11011 C
b1001 F
b11 E
0D
1H
b10 U
b10 >
b11 Q
b11 T
b11 :
b11 =
1+
#168000
0+
#180000
b1000 F
b10000 C
b10 E
b1 <
b1 S
1+
#192000
0+
#204000
b111 F
b111 C
b1 E
b10 S
b10 <
1+
#216000
0+
#228000
b110 F
b10010 C
b11 E
b1 ;
b0 <
b1 R
b0 S
1+
#240000
0+
#252000
b101 F
b1010 C
b10 E
b1 S
b1 <
1+
#264000
0+
#276000
b100 F
b100 C
b1 E
b10 <
b10 S
1+
#288000
0+
#300000
b11 F
b1001 C
b11 E
b10 R
b0 S
b10 ;
b0 <
1+
#312000
0+
#324000
b10 F
b100 C
b10 E
b1 <
b1 S
1+
#336000
0+
#348000
b1 F
b1 C
b1 E
b10 S
b10 <
1+
#360000
0+
#372000
1A
b0 F
b0 C
b0 E
b11 >
b0 ;
b0 <
0H
1G
b11 U
b0 R
b0 S
1+
#384000
0+
#396000
0G
b0 U
1#
b11100010000000110010 !
b11100010000000110010 V
b0 >
1$
b11100010000000110010 "
b11100010000000110010 ?
b11 T
b11 =
1+
#408000
0+
#420000
0$
0#
b100000011101100011 /
b100000011101100011 1
b100000011101100011 B
b10000000000000000000000000000000100000000000000000000000000000001 -
b10000000000000000000000000000000100000000000000000000000000000001 0
b10000000000000000000000000000000100000000000000000000000000000001 @
b100000011101100011 Y
b10000000000000000000000000000000100000000000000000000000000000001 X
1+
#432000
0+
#444000
1,
1+
#456000
0+
#468000
b1 >
1D
b1 U
0,
b11 W
1+
#480000
0+
#492000
0A
b1100011 C
b1 F
b1100011 E
0D
1H
b10 U
b10 >
b11 Q
b11 T
b11 :
b11 =
1+
#504000
0+
#516000
1A
b0 F
b0 C
b111 E
b1 <
b1 S
1+
#528000
0+
#540000
b10 E
b10 S
b10 <
1+
#552000
0+
#564000
b1100011 E
b1 ;
b0 <
b1 R
b0 S
1+
#576000
0+
#588000
0A
b111 C
b1 F
b111 E
b1 S
b1 <
1+
#600000
0+
#612000
1A
b0 F
b0 C
b10 E
b10 <
b10 S
1+
#624000
0+
#636000
b1100011 E
b10 R
b0 S
b10 ;
b0 <
1+
#648000
0+
#660000
b111 E
b1 <
b1 S
1+
#672000
0+
#684000
0A
b10 C
b1 F
b10 E
b10 S
b10 <
1+
#696000
0+
#708000
1A
b0 F
b0 C
b0 E
b11 >
b0 ;
b0 <
0H
1G
b11 U
b0 R
b0 S
1+
#720000
0+
#732000
0G
b0 U
1#
b100000011101100011 !
b100000011101100011 V
b0 >
1$
b100000011101100011 "
b100000011101100011 ?
b11 T
b11 =
1+
#744000
0+
#756000
0$
0#
b0 /
b0 1
b0 B
b1000010001011001010101000010110110001100101101010011010100001000010011 -
b1000010001011001010101000010110110001100101101010011010100001000010011 0
b1000010001011001010101000010110110001100101101010011010100001000010011 @
b0 Y
b1000010001011001010101000010110110001100101101010011010100001000010011 X
1+
#768000
0+
#780000
1,
1+
#792000
0+
#804000
b1 >
1D
b1 U
0,
b11 W
1+
#816000
0+
#828000
b10011 F
0D
1H
b10 U
b10 >
b11 Q
b11 T
b11 :
b11 =
1+
#840000
0+
#852000
b1000010 F
b1 <
b1 S
1+
#864000
0+
#876000
b1001101 F
b10 S
b10 <
1+
#888000
0+
#900000
b101101 F
b1 ;
b0 <
b1 R
b0 S
1+
#912000
0+
#924000
b1100011 F
b1 S
b1 <
1+
#936000
0+
#948000
b1011 F
b10 <
b10 S
1+
#960000
0+
#972000
b1010101 F
b10 R
b0 S
b10 ;
b0 <
1+
#984000
0+
#996000
b10110 F
b1 <
b1 S
1+
#1008000
0+
#1020000
b100001 F
b10 S
b10 <
1+
#1032000
0+
#1044000
b0 F
b11 >
b0 ;
b0 <
0H
1G
b11 U
b0 R
b0 S
1+
#1056000
0+
#1068000
0G
b0 U
1#
b0 !
b0 V
b0 >
1$
b0 "
b0 ?
b11 T
b11 =
1+
#1080000
0+
#1092000
0$
0#
b11111110111111101111111 /
b11111110111111101111111 1
b11111110111111101111111 B
b100000011000000110000001111111111111111100000001011111110111111101111111 -
b100000011000000110000001111111111111111100000001011111110111111101111111 0
b100000011000000110000001111111111111111100000001011111110111111101111111 @
b11111110111111101111111 Y
b100000011000000110000001111111111111111100000001011111110111111101111111 X
1+
#1104000
0+
#1116000
1,
1+
#1128000
0+
#1140000
b1 >
1D
b1 U
0,
b11 W
1+
#1152000
0+
#1164000
0A
b11111100000001 C
b1111111 F
b1111111 E
0D
1H
b10 U
b10 >
b11 Q
b11 T
b11 :
b11 =
1+
#1176000
0+
#1188000
b1 <
b1 S
1+
#1200000
0+
#1212000
b10 S
b10 <
1+
#1224000
0+
#1236000
b1111111 C
b1 F
b1 ;
b0 <
b1 R
b0 S
1+
#1248000
0+
#1260000
b1111111110000001 C
b11111111 F
b1 S
b1 <
1+
#1272000
0+
#1284000
b10 <
b10 S
1+
#1296000
0+
#1308000
b1100000011111111 C
b10000001 F
b10 R
b0 S
b10 ;
b0 <
1+
#1320000
0+
#1332000
b1 <
b1 S
1+
#1344000
0+
#1356000
b10 S
b10 <
1+
#1368000
0+
#1380000
1A
b0 E
b0 C
b0 F
b11 >
b0 ;
b0 <
0H
1G
b11 U
b0 R
b0 S
1+
#1392000
0+
#1404000
0G
b0 U
1#
b111111011000000100000011 !
b111111011000000100000011 V
b0 >
1$
b111111011000000100000011 "
b111111011000000100000011 ?
b11 T
b11 =
1+
#1416000
0+
#1428000
0$
0#
b111111000000100100000011 /
b111111000000100100000011 1
b111111000000100100000011 B
b10101111110100000101111110000000110000000000000001110000000111111110 -
b10101111110100000101111110000000110000000000000001110000000111111110 0
b10101111110100000101111110000000110000000000000001110000000111111110 @
b111111000000100100000011 Y
b10101111110100000101111110000000110000000000000001110000000111111110 X
1+
#1440000
0+
#1452000
1,
1+
#1464000
0+
#1476000
b1 >
1D
b1 U
0,
b11 W
1+
#1488000
0+
#1500000
0A
b1111111111111010 C
b11111110 F
b11 E
0D
1H
b10 U
b10 >
b11 Q
b11 T
b11 :
b11 =
1+
#1512000
0+
#1524000
b1 F
b1001 C
b1001 E
b1 <
b1 S
1+
#1536000
0+
#1548000
b111 F
b1111111111100100 C
b11111100 E
b10 S
b10 <
1+
#1560000
0+
#1572000
1A
b0 F
b0 C
b11 E
b1 ;
b0 <
b1 R
b0 S
1+
#1584000
0+
#1596000
0A
b1101100 C
b1100 F
b1001 E
b1 S
b1 <
1+
#1608000
0+
#1620000
b11111000 F
b100000 C
b11111100 E
b10 <
b10 S
1+
#1632000
0+
#1644000
b101 F
b1111 C
b11 E
b10 R
b0 S
b10 ;
b0 <
1+
#1656000
0+
#1668000
b11111101 F
b1111111111100101 C
b1001 E
b1 <
b1 S
1+
#1680000
0+
#1692000
b1010 F
b1111111111011000 C
b11111100 E
b10 S
b10 <
1+
#1704000
0+
#1716000
1A
b0 F
b0 C
b0 E
b11 >
b0 ;
b0 <
0H
1G
b11 U
b0 R
b0 S
1+
#1728000
0+
#1740000
0G
b0 U
1#
b110011001000110011100111 !
b110011001000110011100111 V
b0 >
1$
b110011001000110011100111 "
b110011001000110011100111 ?
b11 T
b11 =
1+
#1752000
0+
#1764000
0$
0#
1+
