lab4/src/matrix_vector_multiplier.v
// Power-optimized NxN Matrix-by-Vector Multiplier (Verilog-2005)
// Reworked from provided baseline: register enables, operand isolation, conditional accumulation.
// Keep functional behavior identical to baseline (same I/O, outputs, and sequencing).
//
// Save as: src/matrix_vector_multiplier.v
// NOTE: Comments with "// LOW-POWER CHANGE" indicate the targeted optimization and why.

module matrix_vector_multiplier #(
    parameter N     = 3, // Matrix/Vector dimension (e.g., 3 for 3x3)
    parameter WIDTH = 8  // Bit-width for each element
)(
    input  wire                   clk,
    input  wire                   rst_n,   // Active-low asynchronous reset
    input  wire                   ena,     // Enable signal to start multiplication

    // PARAMETERIZED Input Ports
    input  wire signed [N*N*WIDTH-1:0] matrix_a,
    input  wire signed [N*WIDTH-1:0]   vector_b,

    // PARAMETERIZED Output Ports
    output reg  signed [N*WIDTH-1:0]   vector_c,
    output reg                         done     // High when the result is ready
);

    // --- INTERNAL PARAMETERS ---
    localparam CNT_WIDTH = (N <= 1) ? 1 : $clog2(N); // handle small N safely
    localparam ACCUM_WIDTH = (2 * WIDTH) + ((N <= 1) ? 1 : $clog2(N));

    // --- INTERNAL STORAGE ---
    // Note: these are registers (flops) synthesized from the sequential blocks below.
    reg signed [WIDTH-1:0]       mat_a_reg [0:N-1][0:N-1];
    reg signed [WIDTH-1:0]       vec_b_reg [0:N-1];
    reg signed [ACCUM_WIDTH-1:0] vec_c_internal [0:N-1];

    // --- FSM AND COUNTERS ---
    reg [1:0] state;
    localparam STATE_IDLE    = 2'b00;
    localparam STATE_LOAD    = 2'b01;
    localparam STATE_COMPUTE = 2'b11;
    localparam STATE_DONE    = 2'b10;

    // Parameterized loop counters (used as indices)
    reg [CNT_WIDTH-1:0] i;
    reg [CNT_WIDTH-1:0] k;

    // integer loop variables for generate-style unpack/pack in procedural blocks
    reg [CNT_WIDTH-1:0] row, col; // Loop iterators for loading/storing

    // --- CLOCK ENABLE SIGNALS (register-enable style gating) ---
    // LOW-POWER CHANGE: create local CE signals so registers update only when needed.
    wire load_ce    = (state == STATE_LOAD);    // used to load matrix & vector registers
    wire compute_ce = (state == STATE_COMPUTE); // used to update accumulator
    wire done_ce    = (state == STATE_DONE);    // used to pack output once

    // --- OPERAND ISOLATION / MULTIPLIER INPUTS ---
    // LOW-POWER CHANGE: provide isolated operands to the multiplier (zero when not computing).
    // We'll compute product combinationally only for the active i,k to avoid wide fanout switching.
    wire signed [WIDTH-1:0] a_isolated = (compute_ce) ? mat_a_reg[i][k] : {WIDTH{1'b0}};
    wire signed [WIDTH-1:0] b_isolated = (compute_ce) ? vec_b_reg[k]    : {WIDTH{1'b0}};

    // multiply into full width (2*WIDTH) then sign-extend to ACCUM_WIDTH
    wire signed [2*WIDTH-1:0] mul_full;
    assign mul_full = a_isolated * b_isolated;

    wire signed [ACCUM_WIDTH-1:0] product;
    assign product = {{(ACCUM_WIDTH-2*WIDTH){mul_full[2*WIDTH-1]}}, mul_full};

    // --- SEQUENTIAL: reset & load into internal registers (with CE) ---
    // LOW-POWER CHANGE: registers only change while their CE is asserted, reducing toggles.
    always @(posedge clk or negedge rst_n) begin
        if (!rst_n) begin
            // Reset all internal registers to zero
            for (row = 0; row < N; row = row + 1) begin
                for (col = 0; col < N; col = col + 1) begin
                    mat_a_reg[row][col] <= {WIDTH{1'b0}};
                end
                vec_b_reg[row] <= {WIDTH{1'b0}};
                vec_c_internal[row] <= {ACCUM_WIDTH{1'b0}};
            end
            // reset FSM & counters
            done <= 1'b0;
            vector_c <= {N*WIDTH{1'b0}};
        end else begin
            // --- LOAD stage ---
            if (load_ce) begin
                // LOW-POWER CHANGE: load registers only when in LOAD state.
                // This prevents the matrix/vector flops from toggling in other states.
                for (row = 0; row < N; row = row + 1) begin
                    for (col = 0; col < N; col = col + 1) begin
                        mat_a_reg[row][col] <= matrix_a[(row*N+col)*WIDTH +: WIDTH];
                    end
                    vec_b_reg[row] <= vector_b[row*WIDTH +: WIDTH];
                    vec_c_internal[row] <= {ACCUM_WIDTH{1'b0}}; // clear accumulator at load
                end
            end

            // --- COMPUTE stage: update a single accumulator per cycle with operand isolation ---
            if (compute_ce) begin
                // LOW-POWER CHANGE: conditional accumulation avoids toggling when operands are zero.
                // Only update vec_c_internal[i] if the operands are both non-zero.
                // This reduces internal switching for adders and the accumulator flop.
                if ((mat_a_reg[i][k] != {WIDTH{1'b0}}) && (vec_b_reg[k] != {WIDTH{1'b0}})) begin
                    vec_c_internal[i] <= vec_c_internal[i] + product;
                end else begin
                    // Keep the register value unchanged to avoid toggling.
                    vec_c_internal[i] <= vec_c_internal[i];
                end
            end

            // --- DONE stage: pack outputs only in DONE (single-cycle write) ---
            if (done_ce) begin
                // LOW-POWER CHANGE: write to vector_c only once in DONE state to reduce bus toggles.
                for (row = 0; row < N; row = row + 1) begin
                    // Truncate accumulator to WIDTH (same behavior as baseline)
                    vector_c[row*WIDTH +: WIDTH] <= vec_c_internal[row][WIDTH-1:0];
                end
                done <= 1'b1;
            end else begin
                // keep done low except the single DONE cycle
                if (state != STATE_DONE) begin
                    done <= 1'b0;
                end
            end
        end
    end

    // --- FSM & index progression (separate block for clarity) ---
    // Keep FSM behavior same as baseline, but progress counters only in compute state.
    always @(posedge clk or negedge rst_n) begin
        if (!rst_n) begin
            state <= STATE_IDLE;
            i <= {CNT_WIDTH{1'b0}};
            k <= {CNT_WIDTH{1'b0}};
        end else begin
            case (state)
                STATE_IDLE: begin
                    if (ena) begin
                        state <= STATE_LOAD;
                    end else begin
                        state <= STATE_IDLE;
                    end
                end

                STATE_LOAD: begin
                    // After the LOAD cycle completes, start COMPUTE with indices reset.
                    i <= {CNT_WIDTH{1'b0}};
                    k <= {CNT_WIDTH{1'b0}};
                    state <= STATE_COMPUTE;
                end

                STATE_COMPUTE: begin
                    // Progress inner/outer loop indices similar to baseline.
                    if (k == N-1) begin
                        k <= {CNT_WIDTH{1'b0}};
                        if (i == N-1) begin
                            i <= {CNT_WIDTH{1'b0}};
                            state <= STATE_DONE;
                        end else begin
                            i <= i + 1;
                        end
                    end else begin
                        k <= k + 1;
                    end
                end

                STATE_DONE: begin
                    // After DONE, return to IDLE (vector_c written in the other sequential block)
                    state <= STATE_IDLE;
                end

                default: state <= STATE_IDLE;
            endcase
        end
    end

    // --- Note on global clock gating & CE ---
    // We used register-enable style gating (CE signals) in the sequential logic above.
    // This is synthesis-friendly: synthesis tools will either keep the enables
    // as gating logic or map them to integrated clock-gating cells if available.
    // This is preferred over manual gating of 'clk' in RTL (which is unsafe/unsupported).
    //
    // If you want stronger gating, enable the synthesis tool's clock-gating or
    // allow ECO to insert dedicated clock-gating cells based on these enables.

endmodule

lab4/src/matrix_vector_multiplier_baseline.v
// Synthesizable NxN Matrix by Nx1 Vector Multiplication Accelerator
// (Fully parameterized, Verilog-2005 compatible)

module matrix_vector_multiplier_baseline #(
    parameter N     = 3, // Matrix/Vector dimension (e.g., 3 for 3x3)
    parameter WIDTH = 8  // Bit-width for each element
)(
    input  wire                   clk,
    input  wire                   rst_n,   // Active-low asynchronous reset
    input  wire                   ena,     // Enable signal to start multiplication

    // PARAMETERIZED Input Ports
    // Flat bus for the NxN matrix: (N*N*WIDTH) total bits
    input  wire signed [N*N*WIDTH-1:0] matrix_a,
    // Flat bus for the Nx1 vector: (N*WIDTH) total bits
    input  wire signed [N*WIDTH-1:0]   vector_b,

    // PARAMETERIZED Output Ports
    // Flat bus for the Nx1 result: (N*WIDTH) total bits
    output reg  signed [N*WIDTH-1:0]   vector_c,
    output reg                         done     // High when the result is ready
);

    // --- INTERNAL PARAMETERS ---
    
    // Calculate the width for our loop counters (e.g., for N=3, we need 2 bits)
    localparam CNT_WIDTH = $clog2(N);

    // Calculate the width for the internal accumulator
    // Product width = WIDTH * WIDTH => 2*WIDTH
    // We add N of these products. Sum can grow by $clog2(N) bits.
    localparam ACCUM_WIDTH = (2 * WIDTH) + $clog2(N);

    // --- INTERNAL STORAGE ---
    
    // PARAMETERIZED 2D register for the matrix and 1D for the vectors
    reg signed [WIDTH-1:0]       mat_a [0:N-1][0:N-1];
    reg signed [WIDTH-1:0]       vec_b [0:N-1];
    reg signed [ACCUM_WIDTH-1:0] vec_c_internal [0:N-1]; // Wider for accumulation

    // --- FSM AND COUNTERS ---
    reg [1:0] state;
    localparam STATE_IDLE    = 2'b00;
    localparam STATE_LOAD    = 2'b01;
    localparam STATE_COMPUTE = 2'b10;
    localparam STATE_DONE    = 2'b11;

    // PARAMETERIZED loop counters
    reg [CNT_WIDTH-1:0] i, k;    // Loop indices for rows and inner product
    reg [CNT_WIDTH-1:0] row, col; // Loop iterators for loading/storing

    // On every clock cycle, manage the state machine
    always @(posedge clk or negedge rst_n) begin
        if (!rst_n) begin
            // --- RESET STATE ---
            state <= STATE_IDLE;
            done  <= 1'b0;
            i     <= 0;
            k     <= 0;
        end else begin
            case (state)
                STATE_IDLE: begin
                    done <= 1'b0;
                    if (ena) begin
                        state <= STATE_LOAD; // Start on enable signal
                    end
                end

                STATE_LOAD: begin
                    // --- LOAD AND UNPACK INPUTS ---
                    // This 'for' loop is unrolled by the synthesizer
                    for (row = 0; row < N; row = row + 1) begin
                        for (col = 0; col < N; col = col + 1) begin
                            // PARAMETERIZED unpacking logic
                            mat_a[row][col] <= matrix_a[(row*N+col)*WIDTH +: WIDTH];
                        end
                        vec_b[row] <= vector_b[row*WIDTH +: WIDTH];
                        vec_c_internal[row] <= 0; // Clear previous result
                    end
                    i <= 0;
                    k <= 0;
                    state <= STATE_COMPUTE;
                end

                STATE_COMPUTE: begin
                    // --- PERFORM ONE MULTIPLY-ACCUMULATE PER CYCLE ---
                    // C[i] = C[i] + A[i][k] * B[k]
                    vec_c_internal[i] <= vec_c_internal[i] + (mat_a[i][k] * vec_b[k]);

                    // --- PARAMETERIZED LOOP COUNTER UPDATE ---
                    if (k == N-1) begin
                        k <= 0;
                        if (i == N-1) begin
                            i <= 0;
                            state <= STATE_DONE; // Finished all computations
                        end else begin
                            i <= i + 1;
                        end
                    end else begin
                        k <= k + 1;
                    end
                end

                STATE_DONE: begin
                    // --- PACK 1D RESULT VECTOR INTO OUTPUT ---
                    // This 'for' loop is also unrolled
                    for (row = 0; row < N; row = row + 1) begin
                        // PARAMETERIZED packing logic
                        // NOTE: This truncates the wide accumulator result!
                        vector_c[row*WIDTH +: WIDTH] <= vec_c_internal[row][WIDTH-1:0];
                    end
                    done  <= 1'b1;
                    state <= STATE_IDLE; // Return to idle
                end

                default: begin
                    state <= STATE_IDLE;
                end
            endcase
        end
    end

endmodule

lab4/src/matrix_vector_multiplier_opt_tb.v
`timescale 1ns/1ps

// Testbench compares the OPT design (matrix_vector_multiplier)
// against the baseline (matrix_vector_multiplier_baseline)
// using only Verilog-2001 constructs, no SV-only features.

module matrix_vector_multiplier_opt_tb;

  // -------- Parameters --------
  localparam integer N          = 3;
  localparam integer WIDTH      = 8;
  localparam integer CLK_PERIOD = 25;

  // Derived widths
  localparam integer MATRIX_A_WIDTH = N*N*WIDTH;
  localparam integer VECTOR_B_WIDTH = N*WIDTH;
  localparam integer VECTOR_C_WIDTH = N*WIDTH;

  // -------- DUT I/O --------
  reg                      clk;
  reg                      rst_n;
  reg                      ena;

  reg  signed [MATRIX_A_WIDTH-1:0] matrix_a;  // flattened N×N matrix
  reg  signed [VECTOR_B_WIDTH-1:0] vector_b;  // flattened N vector

  wire signed [VECTOR_C_WIDTH-1:0] vector_c_baseline;
  wire                             done_baseline;

  wire signed [VECTOR_C_WIDTH-1:0] vector_c_opt;
  wire                             done_opt;

  // -------- Instantiate Baseline DUT --------
  matrix_vector_multiplier_baseline #(
    .N(N), .WIDTH(WIDTH)
  ) dut_baseline (
    .clk      (clk),
    .rst_n    (rst_n),
    .ena      (ena),
    .matrix_a (matrix_a),
    .vector_b (vector_b),
    .vector_c (vector_c_baseline),
    .done     (done_baseline)
  );

  // -------- Instantiate Optimized DUT --------
  matrix_vector_multiplier #(
    .N(N), .WIDTH(WIDTH)
  ) dut_opt (
    .clk      (clk),
    .rst_n    (rst_n),
    .ena      (ena),
    .matrix_a (matrix_a),
    .vector_b (vector_b),
    .vector_c (vector_c_opt),
    .done     (done_opt)
  );

  // -------- Clock --------
  initial begin
    clk = 1'b0;
    forever #(CLK_PERIOD/2) clk = ~clk;
  end

  // -------- Simple reset task --------
  task do_reset;
  begin
    rst_n    = 1'b0;
    ena      = 1'b0;
    matrix_a = {MATRIX_A_WIDTH{1'b0}};
    vector_b = {VECTOR_B_WIDTH{1'b0}};
    repeat (3) @(posedge clk);
    rst_n = 1'b1;
    @(posedge clk);
  end
  endtask

  // -------- Apply one stimulus and check equality --------
  task apply_and_check(
    input signed [MATRIX_A_WIDTH-1:0] m,
    input signed [VECTOR_B_WIDTH-1:0] v
  );
  begin
    // Drive inputs
    matrix_a <= m;
    vector_b <= v;

    // Pulse enable for one cycle
    @(posedge clk);
    ena <= 1'b1;
    @(posedge clk);
    ena <= 1'b0;

    // Wait for both designs to assert done
    wait(done_baseline && done_opt);
    @(posedge clk);

    // Compare results (bit-accurate)
    if (vector_c_opt !== vector_c_baseline) begin
      $display("[%0t] FAIL", $time);
      $display("  baseline: %0d (0x%0h)", $signed(vector_c_baseline), vector_c_baseline);
      $display("  opt     : %0d (0x%0h)", $signed(vector_c_opt),      vector_c_opt);
      $fatal;
    end else begin
      $display("[%0t] PASS -> c = %0d (0x%0h)",
               $time, $signed(vector_c_opt), vector_c_opt);
    end
  end
  endtask

  // -------- Test sequence --------
  initial begin
    // Waves
    $dumpfile("opt_vs_baseline_waves.vcd");
    $dumpvars(0, matrix_vector_multiplier_opt_tb);

    // Reset
    do_reset();

    // ========== Packing convention ==========
    // We pack MSB-first in concatenations below.
    // For matrix_a: {a00, a01, a02, a10, a11, a12, a20, a21, a22}
    // For vector_b: {b0, b1, b2}
    // Make sure your DUTs use the same convention.

    // -------- TC1: Simple Positive Values --------
    $display("---- TC1: simple positive ----");
    apply_and_check(
      // A = [[1,2,3],[4,5,6],[7,8,9]]
      {
        8'sd1, 8'sd2, 8'sd3,
        8'sd4, 8'sd5, 8'sd6,
        8'sd7, 8'sd8, 8'sd9
      },
      // b = [1,2,3]
      { 8'sd1, 8'sd2, 8'sd3 }
    );

    // -------- TC2: Identity Matrix --------
    $display("---- TC2: identity * vector ----");
    apply_and_check(
      // A = I3
      {
        8'sd1, 8'sd0, 8'sd0,
        8'sd0, 8'sd1, 8'sd0,
        8'sd0, 8'sd0, 8'sd1
      },
      // b = [2,7,99]
      { 8'sd2, 8'sd7, 8'sd99 }
    );

    // -------- TC3: Zero Vector --------
    $display("---- TC3: zero vector ----");
    apply_and_check(
      {
        8'sd33, 8'sd22, 8'sd85,
        8'sd11, 8'sd99, 8'sd45,
        8'sd77, 8'sd66, 8'sd19
      },
      { 8'sd0, 8'sd0, 8'sd0 }
    );

    // -------- TC4: Min/Max Stress (signed) --------
    $display("---- TC4: min/max signed ----");
    // A rows: [-127 -127 -127], [-1 -1 1], [127 127 127]
    apply_and_check(
      {
        -8'sd127, -8'sd127, -8'sd127,
        -8'sd1,   -8'sd1,    8'sd1,
         8'sd127,  8'sd127,  8'sd127
      },
      { 8'sd127, 8'sd127, 8'sd127 }
    );

    // -------- TC5: Mixed signs --------
    $display("---- TC5: mixed signs ----");
    apply_and_check(
      {
         8'sd10,  -8'sd3,  8'sd5,
        -8'sd8,    8'sd12, 8'sd0,
         8'sd7,    8'sd1, -8'sd2
      },
      { -8'sd4, 8'sd9, 8'sd3 }
    );

    $display("[%0t] All tests passed.", $time);
    $finish;
  end

endmodule

lab4/opt_vs_baseline_waves.vcd
$date
	Wed Oct 29 10:28:19 2025
$end
$version
	Icarus Verilog
$end
$timescale
	1ps
$end
$scope module matrix_vector_multiplier_opt_tb $end
$var wire 24 ! vector_c_opt [23:0] $end
$var wire 24 " vector_c_baseline [23:0] $end
$var wire 1 # done_opt $end
$var wire 1 $ done_baseline $end
$var parameter 32 % CLK_PERIOD $end
$var parameter 32 & MATRIX_A_WIDTH $end
$var parameter 32 ' N $end
$var parameter 32 ( VECTOR_B_WIDTH $end
$var parameter 32 ) VECTOR_C_WIDTH $end
$var parameter 32 * WIDTH $end
$var reg 1 + clk $end
$var reg 1 , ena $end
$var reg 72 - matrix_a [71:0] $end
$var reg 1 . rst_n $end
$var reg 24 / vector_b [23:0] $end
$scope module dut_baseline $end
$var wire 1 + clk $end
$var wire 1 , ena $end
$var wire 72 0 matrix_a [71:0] $end
$var wire 1 . rst_n $end
$var wire 24 1 vector_b [23:0] $end
$var parameter 65 2 ACCUM_WIDTH $end
$var parameter 32 3 CNT_WIDTH $end
$var parameter 32 4 N $end
$var parameter 2 5 STATE_COMPUTE $end
$var parameter 2 6 STATE_DONE $end
$var parameter 2 7 STATE_IDLE $end
$var parameter 2 8 STATE_LOAD $end
$var parameter 32 9 WIDTH $end
$var reg 2 : col [1:0] $end
$var reg 1 $ done $end
$var reg 2 ; i [1:0] $end
$var reg 2 < k [1:0] $end
$var reg 2 = row [1:0] $end
$var reg 2 > state [1:0] $end
$var reg 24 ? vector_c [23:0] $end
$upscope $end
$scope module dut_opt $end
$var wire 1 + clk $end
$var wire 1 , ena $end
$var wire 72 @ matrix_a [71:0] $end
$var wire 1 . rst_n $end
$var wire 24 A vector_b [23:0] $end
$var wire 18 B product [17:0] $end
$var wire 16 C mul_full [15:0] $end
$var wire 1 D load_ce $end
$var wire 1 E done_ce $end
$var wire 1 F compute_ce $end
$var wire 8 G b_isolated [7:0] $end
$var wire 8 H a_isolated [7:0] $end
$var parameter 65 I ACCUM_WIDTH $end
$var parameter 32 J CNT_WIDTH $end
$var parameter 32 K N $end
$var parameter 2 L STATE_COMPUTE $end
$var parameter 2 M STATE_DONE $end
$var parameter 2 N STATE_IDLE $end
$var parameter 2 O STATE_LOAD $end
$var parameter 32 P WIDTH $end
$var reg 2 Q col [1:0] $end
$var reg 1 # done $end
$var reg 2 R i [1:0] $end
$var reg 2 S k [1:0] $end
$var reg 2 T row [1:0] $end
$var reg 2 U state [1:0] $end
$var reg 24 V vector_c [23:0] $end
$upscope $end
$scope task apply_and_check $end
$var reg 72 W m [71:0] $end
$var reg 24 X v [23:0] $end
$upscope $end
$scope task do_reset $end
$upscope $end
$upscope $end
$enddefinitions $end
$comment Show the parameter values. $end
$dumpall
b1000 P
b1 O
b0 N
b10 M
b11 L
b11 K
b10 J
b10010 I
b1000 9
b1 8
b0 7
b11 6
b10 5
b11 4
b10 3
b10010 2
b1000 *
b11000 )
b11000 (
b11 '
b1001000 &
b11001 %
$end
#0
$dumpvars
bx X
bx W
b0 V
b0 U
b11 T
b0 S
b0 R
b11 Q
b0 H
b0 G
0F
0E
0D
b0 C
b0 B
b0 A
b0 @
bx ?
b0 >
bx =
b0 <
b0 ;
bx :
b0 1
b0 0
b0 /
0.
b0 -
0,
0+
0$
0#
bx "
b0 !
$end
#12000
b11 Q
b11 T
1+
#24000
0+
#36000
b11 Q
b11 T
1+
#48000
0+
#60000
1.
1+
#72000
0+
#84000
b10000001000000011 /
b10000001000000011 1
b10000001000000011 A
b10000001000000011000001000000010100000110000001110000100000001001 -
b10000001000000011000001000000010100000110000001110000100000001001 0
b10000001000000011000001000000010100000110000001110000100000001001 @
b10000001000000011 X
b10000001000000011000001000000010100000110000001110000100000001001 W
1+
#96000
0+
#108000
1,
1+
#120000
0+
#132000
b1 >
1D
b1 U
0,
1+
#144000
0+
#156000
b11011 B
b11011 C
b1001 H
b11 G
0D
1F
b11 U
b10 >
b11 Q
b11 T
b11 :
b11 =
1+
#168000
0+
#180000
b1000 H
b10000 B
b10000 C
b10 G
b1 <
b1 S
1+
#192000
0+
#204000
b111 H
b111 B
b111 C
b1 G
b10 S
b10 <
1+
#216000
0+
#228000
b110 H
b10010 B
b10010 C
b11 G
b1 ;
b0 <
b1 R
b0 S
1+
#240000
0+
#252000
b101 H
b1010 B
b1010 C
b10 G
b1 S
b1 <
1+
#264000
0+
#276000
b100 H
b100 B
b100 C
b1 G
b10 <
b10 S
1+
#288000
0+
#300000
b11 H
b1001 B
b1001 C
b11 G
b10 R
b0 S
b10 ;
b0 <
1+
#312000
0+
#324000
b10 H
b100 B
b100 C
b10 G
b1 <
b1 S
1+
#336000
0+
#348000
b1 H
b1 B
b1 C
b1 G
b10 S
b10 <
1+
#360000
0+
#372000
b0 H
b0 B
b0 C
b0 G
b11 >
b0 ;
b0 <
0F
1E
b10 U
b0 R
b0 S
1+
#384000
0+
#396000
0E
b0 U
1#
b11100010000000110010 !
b11100010000000110010 V
b0 >
1$
b11100010000000110010 "
b11100010000000110010 ?
b11 T
b11 =
1+
#408000
0+
#420000
0$
0#
b100000011101100011 /
b100000011101100011 1
b100000011101100011 A
b10000000000000000000000000000000100000000000000000000000000000001 -
b10000000000000000000000000000000100000000000000000000000000000001 0
b10000000000000000000000000000000100000000000000000000000000000001 @
b100000011101100011 X
b10000000000000000000000000000000100000000000000000000000000000001 W
1+
#432000
0+
#444000
1,
1+
#456000
0+
#468000
b1 >
1D
b1 U
0,
1+
#480000
0+
#492000
b1100011 B
b1100011 C
b1 H
b1100011 G
0D
1F
b11 U
b10 >
b11 Q
b11 T
b11 :
b11 =
1+
#504000
0+
#516000
b0 H
b0 B
b0 C
b111 G
b1 <
b1 S
1+
#528000
0+
#540000
b10 G
b10 S
b10 <
1+
#552000
0+
#564000
b1100011 G
b1 ;
b0 <
b1 R
b0 S
1+
#576000
0+
#588000
b111 B
b111 C
b1 H
b111 G
b1 S
b1 <
1+
#600000
0+
#612000
b0 H
b0 B
b0 C
b10 G
b10 <
b10 S
1+
#624000
0+
#636000
b1100011 G
b10 R
b0 S
b10 ;
b0 <
1+
#648000
0+
#660000
b111 G
b1 <
b1 S
1+
#672000
0+
#684000
b10 B
b10 C
b1 H
b10 G
b10 S
b10 <
1+
#696000
0+
#708000
b0 H
b0 B
b0 C
b0 G
b11 >
b0 ;
b0 <
0F
1E
b10 U
b0 R
b0 S
1+
#720000
0+
#732000
0E
b0 U
1#
b100000011101100011 !
b100000011101100011 V
b0 >
1$
b100000011101100011 "
b100000011101100011 ?
b11 T
b11 =
1+
#744000
0+
#756000
0$
0#
b0 /
b0 1
b0 A
b1000010001011001010101000010110110001100101101010011010100001000010011 -
b1000010001011001010101000010110110001100101101010011010100001000010011 0
b1000010001011001010101000010110110001100101101010011010100001000010011 @
b0 X
b1000010001011001010101000010110110001100101101010011010100001000010011 W
1+
#768000
0+
#780000
1,
1+
#792000
0+
#804000
b1 >
1D
b1 U
0,
1+
#816000
0+
#828000
b10011 H
0D
1F
b11 U
b10 >
b11 Q
b11 T
b11 :
b11 =
1+
#840000
0+
#852000
b1000010 H
b1 <
b1 S
1+
#864000
0+
#876000
b1001101 H
b10 S
b10 <
1+
#888000
0+
#900000
b101101 H
b1 ;
b0 <
b1 R
b0 S
1+
#912000
0+
#924000
b1100011 H
b1 S
b1 <
1+
#936000
0+
#948000
b1011 H
b10 <
b10 S
1+
#960000
0+
#972000
b1010101 H
b10 R
b0 S
b10 ;
b0 <
1+
#984000
0+
#996000
b10110 H
b1 <
b1 S
1+
#1008000
0+
#1020000
b100001 H
b10 S
b10 <
1+
#1032000
0+
#1044000
b0 H
b11 >
b0 ;
b0 <
0F
1E
b10 U
b0 R
b0 S
1+
#1056000
0+
#1068000
0E
b0 U
1#
b0 !
b0 V
b0 >
1$
b0 "
b0 ?
b11 T
b11 =
1+
#1080000
0+
#1092000
0$
0#
b11111110111111101111111 /
b11111110111111101111111 1
b11111110111111101111111 A
b100000011000000110000001111111111111111100000001011111110111111101111111 -
b100000011000000110000001111111111111111100000001011111110111111101111111 0
b100000011000000110000001111111111111111100000001011111110111111101111111 @
b11111110111111101111111 X
b100000011000000110000001111111111111111100000001011111110111111101111111 W
1+
#1104000
0+
#1116000
1,
1+
#1128000
0+
#1140000
b1 >
1D
b1 U
0,
1+
#1152000
0+
#1164000
b11111100000001 B
b11111100000001 C
b1111111 H
b1111111 G
0D
1F
b11 U
b10 >
b11 Q
b11 T
b11 :
b11 =
1+
#1176000
0+
#1188000
b1 <
b1 S
1+
#1200000
0+
#1212000
b10 S
b10 <
1+
#1224000
0+
#1236000
b1111111 B
b1111111 C
b1 H
b1 ;
b0 <
b1 R
b0 S
1+
#1248000
0+
#1260000
b111111111110000001 B
b1111111110000001 C
b11111111 H
b1 S
b1 <
1+
#1272000
0+
#1284000
b10 <
b10 S
1+
#1296000
0+
#1308000
b111100000011111111 B
b1100000011111111 C
b10000001 H
b10 R
b0 S
b10 ;
b0 <
1+
#1320000
0+
#1332000
b1 <
b1 S
1+
#1344000
0+
#1356000
b10 S
b10 <
1+
#1368000
0+
#1380000
b0 G
b0 B
b0 C
b0 H
b11 >
b0 ;
b0 <
0F
1E
b10 U
b0 R
b0 S
1+
#1392000
0+
#1404000
0E
b0 U
1#
b111111011000000100000011 !
b111111011000000100000011 V
b0 >
1$
b111111011000000100000011 "
b111111011000000100000011 ?
b11 T
b11 =
1+
#1416000
0+
#1428000
0$
0#
b111111000000100100000011 /
b111111000000100100000011 1
b111111000000100100000011 A
b10101111110100000101111110000000110000000000000001110000000111111110 -
b10101111110100000101111110000000110000000000000001110000000111111110 0
b10101111110100000101111110000000110000000000000001110000000111111110 @
b111111000000100100000011 X
b10101111110100000101111110000000110000000000000001110000000111111110 W
1+
#1440000
0+
#1452000
1,
1+
#1464000
0+
#1476000
b1 >
1D
b1 U
0,
1+
#1488000
0+
#1500000
b111111111111111010 B
b1111111111111010 C
b11111110 H
b11 G
0D
1F
b11 U
b10 >
b11 Q
b11 T
b11 :
b11 =
1+
#1512000
0+
#1524000
b1 H
b1001 B
b1001 C
b1001 G
b1 <
b1 S
1+
#1536000
0+
#1548000
b111 H
b111111111111100100 B
b1111111111100100 C
b11111100 G
b10 S
b10 <
1+
#1560000
0+
#1572000
b0 H
b0 B
b0 C
b11 G
b1 ;
b0 <
b1 R
b0 S
1+
#1584000
0+
#1596000
b1101100 B
b1101100 C
b1100 H
b1001 G
b1 S
b1 <
1+
#1608000
0+
#1620000
b11111000 H
b100000 B
b100000 C
b11111100 G
b10 <
b10 S
1+
#1632000
0+
#1644000
b101 H
b1111 B
b1111 C
b11 G
b10 R
b0 S
b10 ;
b0 <
1+
#1656000
0+
#1668000
b11111101 H
b111111111111100101 B
b1111111111100101 C
b1001 G
b1 <
b1 S
1+
#1680000
0+
#1692000
b1010 H
b111111111111011000 B
b1111111111011000 C
b11111100 G
b10 S
b10 <
1+
#1704000
0+
#1716000
b0 H
b0 B
b0 C
b0 G
b11 >
b0 ;
b0 <
0F
1E
b10 U
b0 R
b0 S
1+
#1728000
0+
#1740000
0E
b0 U
1#
b110011001000110011100111 !
b110011001000110011100111 V
b0 >
1$
b110011001000110011100111 "
b110011001000110011100111 ?
b11 T
b11 =
1+
#1752000
0+
#1764000
0$
0#
1+
