LAB2/src/debouncer.v
// STUDENT TO COMPLETE THIS MODULE
// This module must be a synthesizable, synchronous hardware implementation
// of a button debouncer.

// =================================================================
// DELIVERABLE QUESTION:
// Explain why the FSM's ability to check the button state *during*
// the debounce delay is critical for rejecting noise.
//
// YOUR ANSWER:
// [Write your answer here]
//
// =================================================================

module debouncer #(
    parameter DEBOUNCE_CYCLES = 5
)(
    input wire clk,
    input wire reset,
    input wire noisy_button,
    output wire clean_pulse
);

    // Your implementation goes here.
    //
    // 1. Define localparams for your FSM states (e.g., IDLE, DEBOUNCE, PRESSED).
    //
    // 2. Define registers for your state machine and counter.
    //
    // 3. Implement the sequential logic (`always @(posedge clk...)`) for the registers.
    //
    // 4. Implement the combinational logic (`always @(*)`) for the next-state
    //    and counter logic. This is where you will check if the button is
    //    still pressed during the DEBOUNCE state.
    //
    // 5. Implement the output logic to generate a single-cycle pulse.

    localparam IDLE = 2'b00, DEBOUNCE = 2'b01, PRESSED = 2'b10;

    reg [1:0] state, next_state;
    reg [2:0] counter;
    reg clean_pulse_reg;


    always @(posedge clk or posedge reset) begin
        if (reset) begin
            counter <= 0;
            clean_pulse_reg <= 0;
        end else begin
            if (state == DEBOUNCE) begin
                counter <= counter + 1;
            end else begin
                counter <= 0;
            end
        end
    end

    always @(*) begin
        case (state)
            IDLE: begin
                if (!noisy_button) begin
                    next_state = DEBOUNCE;
                end else begin
                    next_state = IDLE;
                end
            end
            DEBOUNCE: begin
                if(noisy_button) begin
                    next_state = IDLE;
                end else if (counter == DEBOUNCE_CYCLES-1) begin
                    next_state = PRESSED;
                end else begin
                    next_state = DEBOUNCE;
                end
            end
            PRESSED: begin
                next_state = PRESSED;
            end
        endcase
    end

    always @(posedge clk or posedge reset) begin
        if (reset) begin
            state <= IDLE;
        end else begin
            state <= next_state;
        end
    end


    // always @(*) begin
    //     clean_pulse_reg = 0;
    //     if (state == PRESSED && counter == 0) begin
    //         clean_pulse_reg = 1;
    //     end
    // end

    always @(*) begin

        if (state == PRESSED) begin
            next_state <= IDLE;
            clean_pulse_reg <= 1;
        end else begin
            clean_pulse_reg <= 0;
        end

    end

    assign clean_pulse = clean_pulse_reg;

endmodule

lab2/src/debouncer_tb.v
// This module is a NON-SYNTHESIZABLE, synchronous behavioral model.
// It uses `repeat` and event controls to model the debouncer's behavior
// in a cycle-accurate way, but without describing implementable hardware.
module debouncer_tb #(
    parameter DEBOUNCE_CYCLES = 5
)(
    input wire clk,
    input wire reset,
    input wire noisy_button,
    output reg clean_pulse
);

    always @(posedge clk or posedge reset) begin
        if (reset) begin
            clean_pulse <= 1'b0;
        end else begin
            // Default to pulse low
            clean_pulse <= 1'b0;

            // Wait for a button press (negedge)
            if (noisy_button == 1'b0) begin
                
                // This is the non-synthesizable part. A real FSM would
                // use a counter. This `repeat` block is for simulation only.
                repeat(DEBOUNCE_CYCLES) @(posedge clk);

                // After waiting, if the button is still pressed, it's valid.
                if (noisy_button == 1'b0) begin
                    clean_pulse <= 1'b1;
                end
            end
        end
    end

endmodule

LAB2/src/verify_debouncer.v
`timescale 1ns/1ps
module verify_debouncer;

    // Parameters
    localparam CLK_PERIOD      = 10;
    localparam DEBOUNCE_CYCLES = 5;

    // Signals
    reg clk;
    reg reset;
    reg noisy_button;

    wire clean_pulse_tb;
    wire clean_pulse_synth;

    // Instantiate Behavioral Model
    debouncer_tb #(
        .DEBOUNCE_CYCLES(DEBOUNCE_CYCLES)
    ) tb_version (
        .clk(clk),
        .reset(reset),
        .noisy_button(noisy_button),
        .clean_pulse(clean_pulse_tb)
    );

    // Instantiate Synthesizable Hardware (Student's Version)
    debouncer #(
        .DEBOUNCE_CYCLES(DEBOUNCE_CYCLES)
    ) synth_version (
        .clk(clk),
        .reset(reset),
        .noisy_button(noisy_button),
        .clean_pulse(clean_pulse_synth)
    );

    // Clock generator
    initial begin
        clk = 0;
        forever #(CLK_PERIOD/2) clk = ~clk;
    end

    // Test Stimulus
    initial begin
        $dumpfile("debouncer_waves.vcd");
        $dumpvars(0, verify_debouncer);
        
        // --- Initial State ---
        noisy_button <= 1; // Button is not pressed
        reset <= 1;
        #(CLK_PERIOD * 2);
        reset <= 0;
        #(CLK_PERIOD * 5);

        // --- SCENARIO 1: A clean, valid press ---
        $display("Test 1: Clean Press (should be accepted)");
        noisy_button <= 0; // Press the button
        #(CLK_PERIOD * (DEBOUNCE_CYCLES + 5));
        noisy_button <= 1; // Release the button
        #(CLK_PERIOD * 5);

        // --- SCENARIO 2: A short noise pulse ---
        $display("Test 2: Short Noise Pulse (should be rejected)");
        noisy_button <= 0;
        #(CLK_PERIOD * 1); // Shorter than DEBOUNCE_CYCLES
        noisy_button <= 1;
        #(CLK_PERIOD * 5);
        
        // --- SCENARIO 3: A longer, but still invalid noise pulse ---
        $display("Test 3: Almost-Valid Noise Pulse (should be rejected)");
        noisy_button <= 0;
        #(CLK_PERIOD * (DEBOUNCE_CYCLES - 1)); // One cycle too short
        noisy_button <= 1;
        #(CLK_PERIOD * 5);

        // --- SCENARIO 4: Debounce phase interrupted by reset ---
        $display("Test 4: Debounce Interrupted by Reset (should be rejected)");
        noisy_button <= 0;
        #(CLK_PERIOD * (DEBOUNCE_CYCLES - 2)); // Wait for 3 cycles
        reset <= 1; // Assert reset during the debounce wait
        #(CLK_PERIOD * 2);
        reset <= 0;
        noisy_button <= 1; // Release button after reset
        #(CLK_PERIOD * 5);
        
        // --- SCENARIO 5: Output pulse interrupted by reset ---
        $display("Test 5: Pulse Interrupted by Reset (pulse should be cut short)");
        noisy_button <= 0; // Start a valid press
        #(CLK_PERIOD * DEBOUNCE_CYCLES); // Wait for debounce to complete
        // The clean_pulse should go high on the next clock edge.
        // We will interrupt it half a cycle later.
        #(CLK_PERIOD/2);
        reset <= 1; // Assert reset, immediately killing the pulse
        #(CLK_PERIOD * 2);
        reset <= 0;
        noisy_button <= 1;
        #(CLK_PERIOD * 5);

        $finish;
    end

endmodule

LAB2/debouncer_waves.vcd
$date
	Wed Oct 15 00:23:45 2025
$end
$version
	Icarus Verilog
$end
$timescale
	1ps
$end
$scope module verify_debouncer $end
$var wire 1 ! clean_pulse_tb $end
$var wire 1 " clean_pulse_synth $end
$var parameter 32 # CLK_PERIOD $end
$var parameter 32 $ DEBOUNCE_CYCLES $end
$var reg 1 % clk $end
$var reg 1 & noisy_button $end
$var reg 1 ' reset $end
$scope module synth_version $end
$var wire 1 " clean_pulse $end
$var wire 1 % clk $end
$var wire 1 & noisy_button $end
$var wire 1 ' reset $end
$var parameter 2 ( DEBOUNCE $end
$var parameter 32 ) DEBOUNCE_CYCLES $end
$var parameter 2 * IDLE $end
$var parameter 2 + PRESSED $end
$var reg 1 , clean_pulse_reg $end
$var reg 3 - counter [2:0] $end
$var reg 2 . next_state [1:0] $end
$var reg 2 / state [1:0] $end
$upscope $end
$scope module tb_version $end
$var wire 1 % clk $end
$var wire 1 & noisy_button $end
$var wire 1 ' reset $end
$var parameter 32 0 DEBOUNCE_CYCLES $end
$var reg 1 ! clean_pulse $end
$upscope $end
$upscope $end
$enddefinitions $end
$comment Show the parameter values. $end
$dumpall
b101 0
b10 +
b0 *
b101 )
b1 (
b101 $
b1010 #
$end
#0
$dumpvars
b0 /
b0 .
b0 -
0,
1'
1&
0%
0"
0!
$end
#5000
1%
#10000
0%
#15000
1%
#20000
0'
0%
#25000
1%
#30000
0%
#35000
1%
#40000
0%
#45000
1%
#50000
0%
#55000
1%
#60000
0%
#65000
1%
#70000
b1 .
0&
0%
#75000
b1 /
1%
#80000
0%
#85000
b1 -
1%
#90000
0%
#95000
b10 -
1%
#100000
0%
#105000
b11 -
1%
#110000
0%
#115000
b10 .
b100 -
1%
#120000
0%
#125000
1"
1,
b0 .
b10 /
b101 -
1!
1%
#130000
0%
#135000
0"
0,
b1 .
0!
b0 -
b0 /
1%
#140000
0%
#145000
b1 /
1%
#150000
0%
#155000
b1 -
1%
#160000
0%
#165000
b10 -
1%
#170000
b0 .
1&
0%
#175000
b11 -
b0 /
1%
#180000
0%
#185000
b0 -
1%
#190000
0%
#195000
1%
#200000
0%
#205000
1%
#210000
0%
#215000
1%
#220000
b1 .
0&
0%
#225000
b1 /
1%
#230000
b0 .
1&
0%
#235000
b1 -
b0 /
1%
#240000
0%
#245000
b0 -
1%
#250000
0%
#255000
1%
#260000
0%
#265000
1%
#270000
0%
#275000
1%
#280000
b1 .
0&
0%
#285000
b1 /
1%
#290000
0%
#295000
b1 -
1%
#300000
0%
#305000
b10 -
1%
#310000
0%
#315000
b11 -
1%
#320000
b0 .
1&
0%
#325000
b0 /
b100 -
1%
#330000
0%
#335000
b0 -
1%
#340000
0%
#345000
1%
#350000
0%
#355000
1%
#360000
0%
#365000
1%
#370000
b1 .
0&
0%
#375000
b1 /
1%
#380000
0%
#385000
b1 -
1%
#390000
0%
#395000
b10 -
1%
#400000
b0 /
b0 -
1'
0%
#405000
1%
#410000
0%
#415000
1%
#420000
b0 .
1&
0'
0%
#425000
1%
#430000
0%
#435000
1%
#440000
0%
#445000
1%
#450000
0%
#455000
1%
#460000
0%
#465000
1%
#470000
b1 .
0&
0%
#475000
b1 /
1%
#480000
0%
#485000
b1 -
1%
#490000
0%
#495000
b10 -
1%
#500000
0%
#505000
b11 -
1%
#510000
0%
#515000
b10 .
b100 -
1%
#520000
0%
#525000
0"
0,
b1 .
b0 -
b0 /
0!
1'
1%
#530000
0%
#535000
1%
#540000
0%
#545000
b0 .
1&
0'
1%
